kolibri_endless_key_theme/__init__.py
kolibri_endless_key_theme/kolibri_plugin.py
kolibri_endless_key_theme/static/android-chrome-192x192.png
kolibri_endless_key_theme/static/android-chrome-256x256.png
kolibri_endless_key_theme/static/android-chrome-512x512.png
kolibri_endless_key_theme/static/favicon.ico
kolibri_endless_key_theme-0.2.0.dist-info/LICENSE
kolibri_endless_key_theme-0.2.0.dist-info/METADATA
kolibri_endless_key_theme-0.2.0.dist-info/WHEEL
kolibri_endless_key_theme-0.2.0.dist-info/entry_points.txt
kolibri_endless_key_theme-0.2.0.dist-info/top_level.txt
kolibri_endless_key_theme-0.2.0.dist-info/RECORD
