Metadata-Version: 2.1
Name: kolibri-endless-key-theme
Version: 0.2.0
Summary: A plugin to define a custom theme for Endless Key for Kolibri
Home-page: https://github.com/endlessm/kolibri-endless-key-theme
Author: Endless OS Foundation
Author-email: maintainers@endlessos.org
License: MIT
Keywords: kolibri
Classifier: Development Status :: 2 - Pre-Alpha
Classifier: Intended Audience :: Developers
Classifier: License :: OSI Approved :: MIT License
Classifier: Natural Language :: English
Classifier: Programming Language :: Python :: 3
Classifier: Programming Language :: Python :: 3.3
Classifier: Programming Language :: Python :: 3.4
Classifier: Programming Language :: Python :: 3.5
Classifier: Programming Language :: Python :: Implementation :: PyPy
License-File: LICENSE
